yta_audio/__init__.py
yta_audio/edition/__init__.py
yta_audio/edition/effects/__init__.py
yta_audio/edition/effects/slow_reverb.py
yta_audio-0.1.4.dist-info/LICENSE
yta_audio-0.1.4.dist-info/METADATA
yta_audio-0.1.4.dist-info/WHEEL
yta_audio-0.1.4.dist-info/RECORD
