Metadata-Version: 2.3
Name: yta-audio
Version: 0.1.4
Summary: Youtube Autonomous Audio Module.
Author: danialcala94
Author-email: danielalcalavalera@gmail.com
Requires-Python: ==3.9
Classifier: Programming Language :: Python :: 3
Classifier: Programming Language :: Python :: 3.9
